discord_voice/__init__.py
discord_voice-0.0.0.dist-info/LICENSE
discord_voice-0.0.0.dist-info/WHEEL
discord_voice-0.0.0.dist-info/METADATA
discord_voice-0.0.0.dist-info/RECORD
